feliz_milvus/__init__.py
feliz_milvus/collection_tools.py
feliz_milvus/crud_tools.py
feliz_milvus-0.1.8.dist-info/METADATA
feliz_milvus-0.1.8.dist-info/WHEEL
feliz_milvus-0.1.8.dist-info/top_level.txt
feliz_milvus-0.1.8.dist-info/RECORD
