Metadata-Version: 2.4
Name: feliz-milvus
Version: 0.1.8
Summary: A Python package for Milvus Git integration
Home-page: https://github.com/nexuni/feliz_milvus
Author: nexuni
Author-email: chewei.lee@nexuni.com
Classifier: Development Status :: 3 - Alpha
Classifier: Intended Audience :: Developers
Classifier: Topic :: Database
Classifier: Programming Language :: Python :: 3
Classifier: License :: OSI Approved :: MIT License
Classifier: Operating System :: OS Independent
Requires-Python: >=3.7
Requires-Dist: pymilvus>=2.3.0
Requires-Dist: numpy
Dynamic: author
Dynamic: author-email
Dynamic: classifier
Dynamic: home-page
Dynamic: requires-dist
Dynamic: requires-python
Dynamic: summary
